{
      "title": "Agricultural economics stuff",
      "authors": "Dr. Seuss",
      "date": "Feb 2016",
      "abstract": "sldfk adlkf jasd;fl krw g;oub; vba;scjv bas;cvou bwo awg ;awbg ;asljcvb ;aslcjvb a;ldjfb eoufb adouba doufhqefpqhfpqdfj qd fqdp ufdbq dpfuqb dj bdkvj bdkf jadbf kadjfb qeiyf beqkfhbq dfkqh bfqdkf daou adofu dbf kqehfbq efq bfodayd vfoadb qeof.",
      "publisher": "Linus Torvalds",
      "project": "https://test.osf.io/yr6ch/",
      "supplementalMaterials": "NONE",
      "figures": "NONE",
      "license": "Mit License",
      "subject": "Agricultural economics",
      "link": "https://test-mfr.osf.io/render?url=https://test.osf.io/yr6ch/?action=download%26mode=render"
}